sztpd/LICENSE
sztpd/__init__.py
sztpd/__main__.py
sztpd/rfc8572.py
sztpd/sztpd.py
sztpd/yl.py
sztpd-0.0.31.dist-info/METADATA
sztpd-0.0.31.dist-info/NOTICE
sztpd-0.0.31.dist-info/WHEEL
sztpd-0.0.31.dist-info/entry_points.txt
sztpd-0.0.31.dist-info/top_level.txt
sztpd-0.0.31.dist-info/RECORD
