Metadata-Version: 2.2
Name: sztpd
Version: 0.0.31
Summary: Secure Zero Touch Provisioning Daemon (SZTPD)
Home-page: https://watsen.net/products/sztpd
Author: Watsen Networks
Author-email: info@watsen.net
License: Non Production Use License
Project-URL: Documentation, https://watsen.net/docs/sztpd
Project-URL: License, https://watsen.net/sales/non-production-use.html
Keywords: ietf,rfc,8572,sztp,secure,zero,touch,provisioning,ztp,secure sztp,zerotouch
Classifier: Development Status :: 2 - Pre-Alpha
Classifier: Environment :: Console
Classifier: Intended Audience :: Information Technology
Classifier: Intended Audience :: System Administrators
Classifier: Intended Audience :: Telecommunications Industry
Classifier: License :: Other/Proprietary License
Classifier: Natural Language :: English
Classifier: Operating System :: MacOS
Classifier: Operating System :: POSIX :: Linux
Classifier: Programming Language :: Python :: 3.11
Classifier: Programming Language :: Python :: 3.12
Classifier: Topic :: Communications
Classifier: Topic :: Internet
Classifier: Topic :: Security
Requires-Python: <3.13,>=3.11
License-File: NOTICE
Requires-Dist: aiohttp<4.0.0
Requires-Dist: basicauth
Requires-Dist: certvalidator
Requires-Dist: cryptography>3.1
Requires-Dist: passlib
Requires-Dist: pyasn1
Requires-Dist: pyasn1-modules>=0.2.6
Requires-Dist: yangcore==0.0.67
Requires-Dist: yangson>=1.4.15
